adbutils/__init__.py
adbutils/_utils.py
adbutils/_wraps.py
adbutils/adb.py
adbutils/constant.py
adbutils/exceptions.py
adbutils/extra/__init__.py
adbutils/extra/apk/__init__.py
adbutils/extra/minicap/__init__.py
adbutils/extra/minicap/exceptions.py
adbutils/extra/minitouch/__init__.py
adbutils/extra/performance/__init__.py
adbutils/extra/performance/cpu.py
adbutils/extra/performance/exceptions.py
adbutils/extra/performance/fps.py
adbutils/extra/performance/meminfo.py
adbutils/extra/rotation/__init__.py
adbutils/static/ADBKeyboard.apk
adbutils/static/aapt2/arm64-v8a/bin/aapt2
adbutils/static/aapt2/arm64-v8a/lib/libaapt2.so
adbutils/static/aapt2/arm64-v8a/lib64/libaapt2.so
adbutils/static/aapt2/armeabi-v7a/bin/aapt2
adbutils/static/aapt2/armeabi-v7a/lib/libaapt2.so
adbutils/static/aapt2/x86/bin/aapt2
adbutils/static/aapt2/x86/lib/libaapt2.so
adbutils/static/aapt2/x86_64/bin/aapt2
adbutils/static/aapt2/x86_64/lib/libaapt2.so
adbutils/static/aapt2/x86_64/lib64/libaapt2.so
adbutils/static/adb/linux/adb
adbutils/static/adb/linux_arm/adb
adbutils/static/adb/mac/adb
adbutils/static/adb/windows/AdbWinApi.dll
adbutils/static/adb/windows/AdbWinUsbApi.dll
adbutils/static/adb/windows/adb.exe
adbutils/static/busyBox/busybox-armv5l
adbutils/static/busyBox/busybox-armv7l
adbutils/static/busyBox/busybox-armv7m
adbutils/static/busyBox/busybox-armv7r
adbutils/static/busyBox/busybox-armv8l
adbutils/static/stf_libs/arm64-v8a/minicap
adbutils/static/stf_libs/arm64-v8a/minicap-nopie
adbutils/static/stf_libs/arm64-v8a/minitouch
adbutils/static/stf_libs/arm64-v8a/minitouch-nopie
adbutils/static/stf_libs/armeabi/minitouch
adbutils/static/stf_libs/armeabi/minitouch-nopie
adbutils/static/stf_libs/armeabi-v7a/minicap
adbutils/static/stf_libs/armeabi-v7a/minicap-nopie
adbutils/static/stf_libs/armeabi-v7a/minitouch
adbutils/static/stf_libs/armeabi-v7a/minitouch-nopie
adbutils/static/stf_libs/minicap-shared/aosp/libs/android-10/armeabi-v7a/minicap.so
adb_utils-1.0.17.dist-info/LICENSE
adb_utils-1.0.17.dist-info/METADATA
adb_utils-1.0.17.dist-info/WHEEL
adb_utils-1.0.17.dist-info/top_level.txt
adb_utils-1.0.17.dist-info/RECORD
