Metadata-Version: 2.1
Name: adb-utils
Version: 1.0.17
Summary: This is a secondary package of adb
Home-page: https://github.com/hakaboom/adb-utils
Author: hakaboom
Author-email: 1534225986@qq.com
License: Apache License 2.0
Classifier: Programming Language :: Python :: 3
Classifier: License :: OSI Approved :: Apache Software License
Classifier: Operating System :: OS Independent
Requires-Python: >=3.8
License-File: LICENSE
Requires-Dist: loguru (>=0.5.3)
Requires-Dist: baseImage (==1.1.1)
